chromium_session/__init__.py
chromium_session/__main__.py
chromium_session/bookmarks.py
chromium_session/browsers.py
chromium_session/cli.py
chromium_session/history.py
chromium_session/organizer.py
chromium_session/parser.py
chromium_session/writer.py
chromium_session-0.2.0.dist-info/METADATA
chromium_session-0.2.0.dist-info/WHEEL
chromium_session-0.2.0.dist-info/entry_points.txt
chromium_session-0.2.0.dist-info/licenses/LICENSE
chromium_session-0.2.0.dist-info/RECORD
