Metadata-Version: 2.4
Name: chromium-session
Version: 0.2.0
Summary: Parse and analyze Chromium-based browser session files (Chrome, Vivaldi, Brave, Edge) with workspace support, history, bookmarks, and tab organization
Project-URL: Homepage, https://github.com/Asseel-Naji/chromium-session
Project-URL: Repository, https://github.com/Asseel-Naji/chromium-session
Project-URL: Issues, https://github.com/Asseel-Naji/chromium-session/issues
Author-email: Asseel Naji <asseel.naji@gmail.com>
License: MIT
License-File: LICENSE
Keywords: bookmarks,brave,browser,chrome,chromium,edge,history,session,tabs,vivaldi,workspace
Classifier: Development Status :: 4 - Beta
Classifier: Intended Audience :: Developers
Classifier: Intended Audience :: End Users/Desktop
Classifier: License :: OSI Approved :: MIT License
Classifier: Operating System :: POSIX :: Linux
Classifier: Programming Language :: Python :: 3
Classifier: Programming Language :: Python :: 3.12
Classifier: Topic :: Internet :: WWW/HTTP :: Browsers
Classifier: Topic :: Utilities
Requires-Python: >=3.12
Requires-Dist: rich>=14.3.1
Requires-Dist: typer>=0.21.1
